{"nodes": [{"id": "c_work_o_official_src_app_item_page_tsx", "label": "page.tsx", "file_type": "code", "source_file": "C:\\work\\o_official\\src\\app\\item\\page.tsx", "source_location": "L1"}, {"id": "item_page_parsepositiveint", "label": "parsePositiveInt()", "file_type": "code", "source_file": "C:\\work\\o_official\\src\\app\\item\\page.tsx", "source_location": "L15"}, {"id": "item_page_parsesort", "label": "parseSort()", "file_type": "code", "source_file": "C:\\work\\o_official\\src\\app\\item\\page.tsx", "source_location": "L26"}, {"id": "item_page_generatemetadata", "label": "generateMetadata()", "file_type": "code", "source_file": "C:\\work\\o_official\\src\\app\\item\\page.tsx", "source_location": "L33"}, {"id": "item_page_itempage", "label": "ItemPage()", "file_type": "code", "source_file": "C:\\work\\o_official\\src\\app\\item\\page.tsx", "source_location": "L41"}], "edges": [{"source": "c_work_o_official_src_app_item_page_tsx", "target": "next", "relation": "imports_from", "confidence": "EXTRACTED", "source_file": "C:\\work\\o_official\\src\\app\\item\\page.tsx", "source_location": "L1", "weight": 1.0}, {"source": "c_work_o_official_src_app_item_page_tsx", "target": "c_work_o_official_src_features_items_components_publicitemgrid", "relation": "imports_from", "confidence": "EXTRACTED", "source_file": "C:\\work\\o_official\\src\\app\\item\\page.tsx", "source_location": "L2", "weight": 1.0}, {"source": "c_work_o_official_src_app_item_page_tsx", "target": "c_work_o_official_src_lib_items_public", "relation": "imports_from", "confidence": "EXTRACTED", "source_file": "C:\\work\\o_official\\src\\app\\item\\page.tsx", "source_location": "L3", "weight": 1.0}, {"source": "c_work_o_official_src_app_item_page_tsx", "target": "item_page_parsepositiveint", "relation": "contains", "confidence": "EXTRACTED", "source_file": "C:\\work\\o_official\\src\\app\\item\\page.tsx", "source_location": "L15", "weight": 1.0}, {"source": "c_work_o_official_src_app_item_page_tsx", "target": "item_page_parsesort", "relation": "contains", "confidence": "EXTRACTED", "source_file": "C:\\work\\o_official\\src\\app\\item\\page.tsx", "source_location": "L26", "weight": 1.0}, {"source": "c_work_o_official_src_app_item_page_tsx", "target": "item_page_generatemetadata", "relation": "contains", "confidence": "EXTRACTED", "source_file": "C:\\work\\o_official\\src\\app\\item\\page.tsx", "source_location": "L33", "weight": 1.0}, {"source": "c_work_o_official_src_app_item_page_tsx", "target": "item_page_itempage", "relation": "contains", "confidence": "EXTRACTED", "source_file": "C:\\work\\o_official\\src\\app\\item\\page.tsx", "source_location": "L41", "weight": 1.0}, {"source": "item_page_itempage", "target": "item_page_parsepositiveint", "relation": "calls", "confidence": "EXTRACTED", "source_file": "C:\\work\\o_official\\src\\app\\item\\page.tsx", "source_location": "L52", "weight": 1.0}, {"source": "item_page_itempage", "target": "item_page_parsesort", "relation": "calls", "confidence": "EXTRACTED", "source_file": "C:\\work\\o_official\\src\\app\\item\\page.tsx", "source_location": "L54", "weight": 1.0}], "raw_calls": [{"caller_nid": "item_page_parsepositiveint", "callee": "parseInt", "source_file": "C:\\work\\o_official\\src\\app\\item\\page.tsx", "source_location": "L19"}, {"caller_nid": "item_page_parsepositiveint", "callee": "isFinite", "source_file": "C:\\work\\o_official\\src\\app\\item\\page.tsx", "source_location": "L20"}, {"caller_nid": "item_page_itempage", "callee": "getPublishedItemsPage", "source_file": "C:\\work\\o_official\\src\\app\\item\\page.tsx", "source_location": "L49"}]}