{"nodes": [{"id": "c_work_o_official_src_app_api_admin_kpi_targets_route_ts", "label": "route.ts", "file_type": "code", "source_file": "C:\\work\\o_official\\src\\app\\api\\admin\\kpi\\targets\\route.ts", "source_location": "L1"}, {"id": "targets_route_getjstyearmonth", "label": "getJstYearMonth()", "file_type": "code", "source_file": "C:\\work\\o_official\\src\\app\\api\\admin\\kpi\\targets\\route.ts", "source_location": "L103"}, {"id": "targets_route_getseasonfromdate", "label": "getSeasonFromDate()", "file_type": "code", "source_file": "C:\\work\\o_official\\src\\app\\api\\admin\\kpi\\targets\\route.ts", "source_location": "L116"}, {"id": "targets_route_parseseasonkey", "label": "parseSeasonKey()", "file_type": "code", "source_file": "C:\\work\\o_official\\src\\app\\api\\admin\\kpi\\targets\\route.ts", "source_location": "L129"}, {"id": "targets_route_getprevseasonkey", "label": "getPrevSeasonKey()", "file_type": "code", "source_file": "C:\\work\\o_official\\src\\app\\api\\admin\\kpi\\targets\\route.ts", "source_location": "L141"}, {"id": "targets_route_getnextseasonkey", "label": "getNextSeasonKey()", "file_type": "code", "source_file": "C:\\work\\o_official\\src\\app\\api\\admin\\kpi\\targets\\route.ts", "source_location": "L149"}, {"id": "targets_route_buildeditableseasons", "label": "buildEditableSeasons()", "file_type": "code", "source_file": "C:\\work\\o_official\\src\\app\\api\\admin\\kpi\\targets\\route.ts", "source_location": "L157"}, {"id": "targets_route_buildvaluesmatrix", "label": "buildValuesMatrix()", "file_type": "code", "source_file": "C:\\work\\o_official\\src\\app\\api\\admin\\kpi\\targets\\route.ts", "source_location": "L175"}, {"id": "targets_route_builddefaulttargetpayload", "label": "buildDefaultTargetPayload()", "file_type": "code", "source_file": "C:\\work\\o_official\\src\\app\\api\\admin\\kpi\\targets\\route.ts", "source_location": "L202"}, {"id": "targets_route_authorizeasadmin", "label": "authorizeAsAdmin()", "file_type": "code", "source_file": "C:\\work\\o_official\\src\\app\\api\\admin\\kpi\\targets\\route.ts", "source_location": "L212"}, {"id": "targets_route_gettargetpayload", "label": "getTargetPayload()", "file_type": "code", "source_file": "C:\\work\\o_official\\src\\app\\api\\admin\\kpi\\targets\\route.ts", "source_location": "L228"}, {"id": "targets_route_get", "label": "GET()", "file_type": "code", "source_file": "C:\\work\\o_official\\src\\app\\api\\admin\\kpi\\targets\\route.ts", "source_location": "L261"}, {"id": "targets_route_put", "label": "PUT()", "file_type": "code", "source_file": "C:\\work\\o_official\\src\\app\\api\\admin\\kpi\\targets\\route.ts", "source_location": "L277"}], "edges": [{"source": "c_work_o_official_src_app_api_admin_kpi_targets_route_ts", "target": "server", "relation": "imports_from", "confidence": "EXTRACTED", "source_file": "C:\\work\\o_official\\src\\app\\api\\admin\\kpi\\targets\\route.ts", "source_location": "L1", "weight": 1.0}, {"source": "c_work_o_official_src_app_api_admin_kpi_targets_route_ts", "target": "zod", "relation": "imports_from", "confidence": "EXTRACTED", "source_file": "C:\\work\\o_official\\src\\app\\api\\admin\\kpi\\targets\\route.ts", "source_location": "L2", "weight": 1.0}, {"source": "c_work_o_official_src_app_api_admin_kpi_targets_route_ts", "target": "c_work_o_official_src_lib_auth_admin_rbac", "relation": "imports_from", "confidence": "EXTRACTED", "source_file": "C:\\work\\o_official\\src\\app\\api\\admin\\kpi\\targets\\route.ts", "source_location": "L3", "weight": 1.0}, {"source": "c_work_o_official_src_app_api_admin_kpi_targets_route_ts", "target": "c_work_o_official_src_lib_supabase_server", "relation": "imports_from", "confidence": "EXTRACTED", "source_file": "C:\\work\\o_official\\src\\app\\api\\admin\\kpi\\targets\\route.ts", "source_location": "L4", "weight": 1.0}, {"source": "c_work_o_official_src_app_api_admin_kpi_targets_route_ts", "target": "targets_route_getjstyearmonth", "relation": "contains", "confidence": "EXTRACTED", "source_file": "C:\\work\\o_official\\src\\app\\api\\admin\\kpi\\targets\\route.ts", "source_location": "L103", "weight": 1.0}, {"source": "c_work_o_official_src_app_api_admin_kpi_targets_route_ts", "target": "targets_route_getseasonfromdate", "relation": "contains", "confidence": "EXTRACTED", "source_file": "C:\\work\\o_official\\src\\app\\api\\admin\\kpi\\targets\\route.ts", "source_location": "L116", "weight": 1.0}, {"source": "c_work_o_official_src_app_api_admin_kpi_targets_route_ts", "target": "targets_route_parseseasonkey", "relation": "contains", "confidence": "EXTRACTED", "source_file": "C:\\work\\o_official\\src\\app\\api\\admin\\kpi\\targets\\route.ts", "source_location": "L129", "weight": 1.0}, {"source": "c_work_o_official_src_app_api_admin_kpi_targets_route_ts", "target": "targets_route_getprevseasonkey", "relation": "contains", "confidence": "EXTRACTED", "source_file": "C:\\work\\o_official\\src\\app\\api\\admin\\kpi\\targets\\route.ts", "source_location": "L141", "weight": 1.0}, {"source": "c_work_o_official_src_app_api_admin_kpi_targets_route_ts", "target": "targets_route_getnextseasonkey", "relation": "contains", "confidence": "EXTRACTED", "source_file": "C:\\work\\o_official\\src\\app\\api\\admin\\kpi\\targets\\route.ts", "source_location": "L149", "weight": 1.0}, {"source": "c_work_o_official_src_app_api_admin_kpi_targets_route_ts", "target": "targets_route_buildeditableseasons", "relation": "contains", "confidence": "EXTRACTED", "source_file": "C:\\work\\o_official\\src\\app\\api\\admin\\kpi\\targets\\route.ts", "source_location": "L157", "weight": 1.0}, {"source": "c_work_o_official_src_app_api_admin_kpi_targets_route_ts", "target": "targets_route_buildvaluesmatrix", "relation": "contains", "confidence": "EXTRACTED", "source_file": "C:\\work\\o_official\\src\\app\\api\\admin\\kpi\\targets\\route.ts", "source_location": "L175", "weight": 1.0}, {"source": "c_work_o_official_src_app_api_admin_kpi_targets_route_ts", "target": "targets_route_builddefaulttargetpayload", "relation": "contains", "confidence": "EXTRACTED", "source_file": "C:\\work\\o_official\\src\\app\\api\\admin\\kpi\\targets\\route.ts", "source_location": "L202", "weight": 1.0}, {"source": "c_work_o_official_src_app_api_admin_kpi_targets_route_ts", "target": "targets_route_authorizeasadmin", "relation": "contains", "confidence": "EXTRACTED", "source_file": "C:\\work\\o_official\\src\\app\\api\\admin\\kpi\\targets\\route.ts", "source_location": "L212", "weight": 1.0}, {"source": "c_work_o_official_src_app_api_admin_kpi_targets_route_ts", "target": "targets_route_gettargetpayload", "relation": "contains", "confidence": "EXTRACTED", "source_file": "C:\\work\\o_official\\src\\app\\api\\admin\\kpi\\targets\\route.ts", "source_location": "L228", "weight": 1.0}, {"source": "c_work_o_official_src_app_api_admin_kpi_targets_route_ts", "target": "targets_route_get", "relation": "contains", "confidence": "EXTRACTED", "source_file": "C:\\work\\o_official\\src\\app\\api\\admin\\kpi\\targets\\route.ts", "source_location": "L261", "weight": 1.0}, {"source": "c_work_o_official_src_app_api_admin_kpi_targets_route_ts", "target": "targets_route_put", "relation": "contains", "confidence": "EXTRACTED", "source_file": "C:\\work\\o_official\\src\\app\\api\\admin\\kpi\\targets\\route.ts", "source_location": "L277", "weight": 1.0}, {"source": "targets_route_getseasonfromdate", "target": "targets_route_getjstyearmonth", "relation": "calls", "confidence": "EXTRACTED", "source_file": "C:\\work\\o_official\\src\\app\\api\\admin\\kpi\\targets\\route.ts", "source_location": "L117", "weight": 1.0}, {"source": "targets_route_getprevseasonkey", "target": "targets_route_parseseasonkey", "relation": "calls", "confidence": "EXTRACTED", "source_file": "C:\\work\\o_official\\src\\app\\api\\admin\\kpi\\targets\\route.ts", "source_location": "L142", "weight": 1.0}, {"source": "targets_route_getnextseasonkey", "target": "targets_route_parseseasonkey", "relation": "calls", "confidence": "EXTRACTED", "source_file": "C:\\work\\o_official\\src\\app\\api\\admin\\kpi\\targets\\route.ts", "source_location": "L150", "weight": 1.0}, {"source": "targets_route_buildeditableseasons", "target": "targets_route_getprevseasonkey", "relation": "calls", "confidence": "EXTRACTED", "source_file": "C:\\work\\o_official\\src\\app\\api\\admin\\kpi\\targets\\route.ts", "source_location": "L162", "weight": 1.0}, {"source": "targets_route_buildeditableseasons", "target": "targets_route_getnextseasonkey", "relation": "calls", "confidence": "EXTRACTED", "source_file": "C:\\work\\o_official\\src\\app\\api\\admin\\kpi\\targets\\route.ts", "source_location": "L168", "weight": 1.0}, {"source": "targets_route_builddefaulttargetpayload", "target": "targets_route_buildeditableseasons", "relation": "calls", "confidence": "EXTRACTED", "source_file": "C:\\work\\o_official\\src\\app\\api\\admin\\kpi\\targets\\route.ts", "source_location": "L203", "weight": 1.0}, {"source": "targets_route_builddefaulttargetpayload", "target": "targets_route_buildvaluesmatrix", "relation": "calls", "confidence": "EXTRACTED", "source_file": "C:\\work\\o_official\\src\\app\\api\\admin\\kpi\\targets\\route.ts", "source_location": "L208", "weight": 1.0}, {"source": "targets_route_gettargetpayload", "target": "targets_route_getseasonfromdate", "relation": "calls", "confidence": "EXTRACTED", "source_file": "C:\\work\\o_official\\src\\app\\api\\admin\\kpi\\targets\\route.ts", "source_location": "L230", "weight": 1.0}, {"source": "targets_route_gettargetpayload", "target": "targets_route_buildeditableseasons", "relation": "calls", "confidence": "EXTRACTED", "source_file": "C:\\work\\o_official\\src\\app\\api\\admin\\kpi\\targets\\route.ts", "source_location": "L231", "weight": 1.0}, {"source": "targets_route_gettargetpayload", "target": "targets_route_builddefaulttargetpayload", "relation": "calls", "confidence": "EXTRACTED", "source_file": "C:\\work\\o_official\\src\\app\\api\\admin\\kpi\\targets\\route.ts", "source_location": "L244", "weight": 1.0}, {"source": "targets_route_gettargetpayload", "target": "targets_route_buildvaluesmatrix", "relation": "calls", "confidence": "EXTRACTED", "source_file": "C:\\work\\o_official\\src\\app\\api\\admin\\kpi\\targets\\route.ts", "source_location": "L257", "weight": 1.0}, {"source": "targets_route_get", "target": "targets_route_authorizeasadmin", "relation": "calls", "confidence": "EXTRACTED", "source_file": "C:\\work\\o_official\\src\\app\\api\\admin\\kpi\\targets\\route.ts", "source_location": "L263", "weight": 1.0}, {"source": "targets_route_get", "target": "targets_route_gettargetpayload", "relation": "calls", "confidence": "EXTRACTED", "source_file": "C:\\work\\o_official\\src\\app\\api\\admin\\kpi\\targets\\route.ts", "source_location": "L268", "weight": 1.0}, {"source": "targets_route_get", "target": "targets_route_getseasonfromdate", "relation": "calls", "confidence": "EXTRACTED", "source_file": "C:\\work\\o_official\\src\\app\\api\\admin\\kpi\\targets\\route.ts", "source_location": "L272", "weight": 1.0}, {"source": "targets_route_get", "target": "targets_route_builddefaulttargetpayload", "relation": "calls", "confidence": "EXTRACTED", "source_file": "C:\\work\\o_official\\src\\app\\api\\admin\\kpi\\targets\\route.ts", "source_location": "L273", "weight": 1.0}, {"source": "targets_route_put", "target": "targets_route_authorizeasadmin", "relation": "calls", "confidence": "EXTRACTED", "source_file": "C:\\work\\o_official\\src\\app\\api\\admin\\kpi\\targets\\route.ts", "source_location": "L279", "weight": 1.0}, {"source": "targets_route_put", "target": "targets_route_gettargetpayload", "relation": "calls", "confidence": "EXTRACTED", "source_file": "C:\\work\\o_official\\src\\app\\api\\admin\\kpi\\targets\\route.ts", "source_location": "L378", "weight": 1.0}], "raw_calls": [{"caller_nid": "targets_route_getjstyearmonth", "callee": "formatToParts", "source_file": "C:\\work\\o_official\\src\\app\\api\\admin\\kpi\\targets\\route.ts", "source_location": "L110"}, {"caller_nid": "targets_route_getjstyearmonth", "callee": "parseInt", "source_file": "C:\\work\\o_official\\src\\app\\api\\admin\\kpi\\targets\\route.ts", "source_location": "L111"}, {"caller_nid": "targets_route_getjstyearmonth", "callee": "find", "source_file": "C:\\work\\o_official\\src\\app\\api\\admin\\kpi\\targets\\route.ts", "source_location": "L111"}, {"caller_nid": "targets_route_getjstyearmonth", "callee": "parseInt", "source_file": "C:\\work\\o_official\\src\\app\\api\\admin\\kpi\\targets\\route.ts", "source_location": "L112"}, {"caller_nid": "targets_route_getjstyearmonth", "callee": "find", "source_file": "C:\\work\\o_official\\src\\app\\api\\admin\\kpi\\targets\\route.ts", "source_location": "L112"}, {"caller_nid": "targets_route_parseseasonkey", "callee": "match", "source_file": "C:\\work\\o_official\\src\\app\\api\\admin\\kpi\\targets\\route.ts", "source_location": "L130"}, {"caller_nid": "targets_route_parseseasonkey", "callee": "parseInt", "source_file": "C:\\work\\o_official\\src\\app\\api\\admin\\kpi\\targets\\route.ts", "source_location": "L136"}, {"caller_nid": "targets_route_buildeditableseasons", "callee": "unshift", "source_file": "C:\\work\\o_official\\src\\app\\api\\admin\\kpi\\targets\\route.ts", "source_location": "L163"}, {"caller_nid": "targets_route_buildeditableseasons", "callee": "push", "source_file": "C:\\work\\o_official\\src\\app\\api\\admin\\kpi\\targets\\route.ts", "source_location": "L169"}, {"caller_nid": "targets_route_buildvaluesmatrix", "callee": "includes", "source_file": "C:\\work\\o_official\\src\\app\\api\\admin\\kpi\\targets\\route.ts", "source_location": "L192"}, {"caller_nid": "targets_route_authorizeasadmin", "callee": "authorizeAdminPermission", "source_file": "C:\\work\\o_official\\src\\app\\api\\admin\\kpi\\targets\\route.ts", "source_location": "L213"}, {"caller_nid": "targets_route_authorizeasadmin", "callee": "json", "source_file": "C:\\work\\o_official\\src\\app\\api\\admin\\kpi\\targets\\route.ts", "source_location": "L221"}, {"caller_nid": "targets_route_gettargetpayload", "callee": "createServiceRoleClient", "source_file": "C:\\work\\o_official\\src\\app\\api\\admin\\kpi\\targets\\route.ts", "source_location": "L229"}, {"caller_nid": "targets_route_gettargetpayload", "callee": "in", "source_file": "C:\\work\\o_official\\src\\app\\api\\admin\\kpi\\targets\\route.ts", "source_location": "L233"}, {"caller_nid": "targets_route_gettargetpayload", "callee": "select", "source_file": "C:\\work\\o_official\\src\\app\\api\\admin\\kpi\\targets\\route.ts", "source_location": "L233"}, {"caller_nid": "targets_route_gettargetpayload", "callee": "from", "source_file": "C:\\work\\o_official\\src\\app\\api\\admin\\kpi\\targets\\route.ts", "source_location": "L233"}, {"caller_nid": "targets_route_gettargetpayload", "callee": "includes", "source_file": "C:\\work\\o_official\\src\\app\\api\\admin\\kpi\\targets\\route.ts", "source_location": "L242"}, {"caller_nid": "targets_route_gettargetpayload", "callee": "warn", "source_file": "C:\\work\\o_official\\src\\app\\api\\admin\\kpi\\targets\\route.ts", "source_location": "L243"}, {"caller_nid": "targets_route_gettargetpayload", "callee": "warn", "source_file": "C:\\work\\o_official\\src\\app\\api\\admin\\kpi\\targets\\route.ts", "source_location": "L248"}, {"caller_nid": "targets_route_get", "callee": "json", "source_file": "C:\\work\\o_official\\src\\app\\api\\admin\\kpi\\targets\\route.ts", "source_location": "L269"}, {"caller_nid": "targets_route_get", "callee": "error", "source_file": "C:\\work\\o_official\\src\\app\\api\\admin\\kpi\\targets\\route.ts", "source_location": "L271"}, {"caller_nid": "targets_route_get", "callee": "json", "source_file": "C:\\work\\o_official\\src\\app\\api\\admin\\kpi\\targets\\route.ts", "source_location": "L273"}, {"caller_nid": "targets_route_put", "callee": "json", "source_file": "C:\\work\\o_official\\src\\app\\api\\admin\\kpi\\targets\\route.ts", "source_location": "L286"}, {"caller_nid": "targets_route_put", "callee": "error", "source_file": "C:\\work\\o_official\\src\\app\\api\\admin\\kpi\\targets\\route.ts", "source_location": "L288"}, {"caller_nid": "targets_route_put", "callee": "json", "source_file": "C:\\work\\o_official\\src\\app\\api\\admin\\kpi\\targets\\route.ts", "source_location": "L289"}, {"caller_nid": "targets_route_put", "callee": "safeParse", "source_file": "C:\\work\\o_official\\src\\app\\api\\admin\\kpi\\targets\\route.ts", "source_location": "L292"}, {"caller_nid": "targets_route_put", "callee": "error", "source_file": "C:\\work\\o_official\\src\\app\\api\\admin\\kpi\\targets\\route.ts", "source_location": "L294"}, {"caller_nid": "targets_route_put", "callee": "json", "source_file": "C:\\work\\o_official\\src\\app\\api\\admin\\kpi\\targets\\route.ts", "source_location": "L295"}, {"caller_nid": "targets_route_put", "callee": "map", "source_file": "C:\\work\\o_official\\src\\app\\api\\admin\\kpi\\targets\\route.ts", "source_location": "L301"}, {"caller_nid": "targets_route_put", "callee": "filter", "source_file": "C:\\work\\o_official\\src\\app\\api\\admin\\kpi\\targets\\route.ts", "source_location": "L302"}, {"caller_nid": "targets_route_put", "callee": "filter", "source_file": "C:\\work\\o_official\\src\\app\\api\\admin\\kpi\\targets\\route.ts", "source_location": "L304"}, {"caller_nid": "targets_route_put", "callee": "map", "source_file": "C:\\work\\o_official\\src\\app\\api\\admin\\kpi\\targets\\route.ts", "source_location": "L305"}, {"caller_nid": "targets_route_put", "callee": "filter", "source_file": "C:\\work\\o_official\\src\\app\\api\\admin\\kpi\\targets\\route.ts", "source_location": "L305"}, {"caller_nid": "targets_route_put", "callee": "createServiceRoleClient", "source_file": "C:\\work\\o_official\\src\\app\\api\\admin\\kpi\\targets\\route.ts", "source_location": "L313"}, {"caller_nid": "targets_route_put", "callee": "eq", "source_file": "C:\\work\\o_official\\src\\app\\api\\admin\\kpi\\targets\\route.ts", "source_location": "L316"}, {"caller_nid": "targets_route_put", "callee": "eq", "source_file": "C:\\work\\o_official\\src\\app\\api\\admin\\kpi\\targets\\route.ts", "source_location": "L316"}, {"caller_nid": "targets_route_put", "callee": "delete", "source_file": "C:\\work\\o_official\\src\\app\\api\\admin\\kpi\\targets\\route.ts", "source_location": "L316"}, {"caller_nid": "targets_route_put", "callee": "from", "source_file": "C:\\work\\o_official\\src\\app\\api\\admin\\kpi\\targets\\route.ts", "source_location": "L316"}, {"caller_nid": "targets_route_put", "callee": "error", "source_file": "C:\\work\\o_official\\src\\app\\api\\admin\\kpi\\targets\\route.ts", "source_location": "L324"}, {"caller_nid": "targets_route_put", "callee": "stringify", "source_file": "C:\\work\\o_official\\src\\app\\api\\admin\\kpi\\targets\\route.ts", "source_location": "L327"}, {"caller_nid": "targets_route_put", "callee": "json", "source_file": "C:\\work\\o_official\\src\\app\\api\\admin\\kpi\\targets\\route.ts", "source_location": "L331"}, {"caller_nid": "targets_route_put", "callee": "stringify", "source_file": "C:\\work\\o_official\\src\\app\\api\\admin\\kpi\\targets\\route.ts", "source_location": "L341"}, {"caller_nid": "targets_route_put", "callee": "error", "source_file": "C:\\work\\o_official\\src\\app\\api\\admin\\kpi\\targets\\route.ts", "source_location": "L342"}, {"caller_nid": "targets_route_put", "callee": "log", "source_file": "C:\\work\\o_official\\src\\app\\api\\admin\\kpi\\targets\\route.ts", "source_location": "L348"}, {"caller_nid": "targets_route_put", "callee": "upsert", "source_file": "C:\\work\\o_official\\src\\app\\api\\admin\\kpi\\targets\\route.ts", "source_location": "L349"}, {"caller_nid": "targets_route_put", "callee": "from", "source_file": "C:\\work\\o_official\\src\\app\\api\\admin\\kpi\\targets\\route.ts", "source_location": "L349"}, {"caller_nid": "targets_route_put", "callee": "error", "source_file": "C:\\work\\o_official\\src\\app\\api\\admin\\kpi\\targets\\route.ts", "source_location": "L355"}, {"caller_nid": "targets_route_put", "callee": "stringify", "source_file": "C:\\work\\o_official\\src\\app\\api\\admin\\kpi\\targets\\route.ts", "source_location": "L358"}, {"caller_nid": "targets_route_put", "callee": "json", "source_file": "C:\\work\\o_official\\src\\app\\api\\admin\\kpi\\targets\\route.ts", "source_location": "L362"}, {"caller_nid": "targets_route_put", "callee": "stringify", "source_file": "C:\\work\\o_official\\src\\app\\api\\admin\\kpi\\targets\\route.ts", "source_location": "L372"}, {"caller_nid": "targets_route_put", "callee": "error", "source_file": "C:\\work\\o_official\\src\\app\\api\\admin\\kpi\\targets\\route.ts", "source_location": "L373"}, {"caller_nid": "targets_route_put", "callee": "json", "source_file": "C:\\work\\o_official\\src\\app\\api\\admin\\kpi\\targets\\route.ts", "source_location": "L379"}, {"caller_nid": "targets_route_put", "callee": "stringify", "source_file": "C:\\work\\o_official\\src\\app\\api\\admin\\kpi\\targets\\route.ts", "source_location": "L394"}, {"caller_nid": "targets_route_put", "callee": "error", "source_file": "C:\\work\\o_official\\src\\app\\api\\admin\\kpi\\targets\\route.ts", "source_location": "L398"}, {"caller_nid": "targets_route_put", "callee": "json", "source_file": "C:\\work\\o_official\\src\\app\\api\\admin\\kpi\\targets\\route.ts", "source_location": "L404"}]}